orange3_salesforce-0.0.7.dist-info/licenses/LICENSE
orangecontrib/__init__.py
orangecontrib/salesforce/__init__.py
orangecontrib/salesforce/widgets/__init__.py
orangecontrib/salesforce/widgets/owsfcontacts.py
orangecontrib/salesforce/widgets/owsfdcauth.py
orangecontrib/salesforce/widgets/icons/sfdc.svg
orange3_salesforce-0.0.7.dist-info/METADATA
orange3_salesforce-0.0.7.dist-info/WHEEL
orange3_salesforce-0.0.7.dist-info/entry_points.txt
orange3_salesforce-0.0.7.dist-info/top_level.txt
orange3_salesforce-0.0.7.dist-info/RECORD
