Metadata-Version: 2.4
Name: orange3-salesforce
Version: 0.0.7
Summary: Read and manage data in Salesforce
Author-email: Brock Tibert <brocktibert@gmail.com>
License-Expression: CC-BY-NC-SA-4.0
Project-URL: Homepage, https://github.com/btibert3/orange3-salesforce
Keywords: orange3 add-on
Classifier: Development Status :: 3 - Alpha
Classifier: Intended Audience :: Education
Classifier: Intended Audience :: Science/Research
Classifier: Programming Language :: Python :: 3 :: Only
Requires-Python: >=3.11
License-File: LICENSE
Requires-Dist: orange3
Requires-Dist: simple-salesforce
Provides-Extra: test
Requires-Dist: coverage; extra == "test"
Provides-Extra: doc
Requires-Dist: sphinx; extra == "doc"
Requires-Dist: recommonmark; extra == "doc"
Requires-Dist: sphinx_rtd_theme; extra == "doc"
Dynamic: license-file
